huaweicloudsdkocr/__init__.py
huaweicloudsdkocr/v1/__init__.py
huaweicloudsdkocr/v1/ocr_async_client.py
huaweicloudsdkocr/v1/ocr_client.py
huaweicloudsdkocr/v1/model/__init__.py
huaweicloudsdkocr/v1/model/acceptance_bill_request_body.py
huaweicloudsdkocr/v1/model/acceptance_bill_result.py
huaweicloudsdkocr/v1/model/auto_classification_request_body.py
huaweicloudsdkocr/v1/model/auto_classification_result.py
huaweicloudsdkocr/v1/model/auto_classification_result_status.py
huaweicloudsdkocr/v1/model/auto_id_doc_classification_alarm_confidence.py
huaweicloudsdkocr/v1/model/auto_id_doc_classification_alarm_result.py
huaweicloudsdkocr/v1/model/auto_id_doc_classification_request_body.py
huaweicloudsdkocr/v1/model/auto_id_doc_classification_result.py
huaweicloudsdkocr/v1/model/bank_receipt_dict.py
huaweicloudsdkocr/v1/model/bank_receipt_kv_pair.py
huaweicloudsdkocr/v1/model/bank_receipt_request_body.py
huaweicloudsdkocr/v1/model/bank_receipt_result.py
huaweicloudsdkocr/v1/model/bankcard_request_body.py
huaweicloudsdkocr/v1/model/bankcard_result.py
huaweicloudsdkocr/v1/model/belong_item_list.py
huaweicloudsdkocr/v1/model/beneficiary_item.py
huaweicloudsdkocr/v1/model/business_card_request_body.py
huaweicloudsdkocr/v1/model/business_card_result.py
huaweicloudsdkocr/v1/model/business_license_request_body.py
huaweicloudsdkocr/v1/model/business_license_result.py
huaweicloudsdkocr/v1/model/cambodian_id_card_request_body.py
huaweicloudsdkocr/v1/model/cambodian_id_card_result.py
huaweicloudsdkocr/v1/model/cambodian_id_card_score_information_result.py
huaweicloudsdkocr/v1/model/char_list_item.py
huaweicloudsdkocr/v1/model/chile_id_card_confidence.py
huaweicloudsdkocr/v1/model/chile_id_card_request_body.py
huaweicloudsdkocr/v1/model/chile_id_card_result.py
huaweicloudsdkocr/v1/model/colombia_id_card_request_body.py
huaweicloudsdkocr/v1/model/colombia_id_card_result.py
huaweicloudsdkocr/v1/model/custom_template_request_body.py
huaweicloudsdkocr/v1/model/driver_license_back.py
huaweicloudsdkocr-3.1.184.dist-info/METADATA
huaweicloudsdkocr-3.1.184.dist-info/WHEEL
huaweicloudsdkocr-3.1.184.dist-info/licenses/LICENSE
huaweicloudsdkocr-3.1.184.dist-info/RECORD
